{
  "schema_version": "0.1",
  "indicator": {
    "id": "qcew_total_private_employment_annual",
    "title": "QCEW annual average employment, total private, all industries",
    "short_title": "QCEW private employment",
    "provider": "qcew",
    "source_id": "bls_qcew_open_data",
    "series_id": "qcew:US000:private:10:annual_avg_emplvl",
    "group": "industry_state_local",
    "subgroup": "qcew",
    "priority": "recommended",
    "frequency": "A",
    "units": "Jobs",
    "seasonal_adjustment": "NSA",
    "geography": "US",
    "start_year": 1990,
    "release": "QCEW annual averages",
    "source_url": null,
    "documentation_url": null,
    "tags": [
      "qcew",
      "employment",
      "private sector",
      "industry",
      "annual"
    ],
    "aliases": [
      "covered employment",
      "private covered jobs"
    ],
    "notes": "QCEW slice parameters are declared; verify live annual slice parsing and aggregation before promoting beyond recommended.",
    "api_params": {
      "qtr": "A",
      "slice_type": "area",
      "slice_code": "US000",
      "area_fips": "US000",
      "own_code": 5,
      "industry_code": "10",
      "value_field": "annual_avg_emplvl"
    },
    "chart": {
      "default_type": "line",
      "recommended": [
        "line",
        "industry_drilldown"
      ],
      "y_axis_label": "Jobs",
      "show_recession_bands": false,
      "allow_geography_filter": false,
      "allow_demographic_filter": false,
      "allow_industry_filter": false,
      "transformations": [
        "pct_change_12",
        "index_first_100"
      ]
    }
  },
  "observations": [
    {
      "indicator_id": "qcew_total_private_employment_annual",
      "date": "2014-01-01",
      "value": 115568686.0,
      "source": "bls_qcew_open_data",
      "series_id": "qcew:US000:private:10:annual_avg_emplvl",
      "frequency": "A",
      "seasonal_adjustment": "NSA",
      "units": "Jobs",
      "realtime_start": null,
      "realtime_end": null,
      "footnotes": "area_fips=US000; industry_code=10; own_code=5; agglvl_code=11",
      "geography": "US",
      "geo_id": "US",
      "geo_label": "US",
      "entity_key": "qcew_total_private_employment_annual|US",
      "change_1": null,
      "pct_change_1": null,
      "change_3": null,
      "pct_change_3": null,
      "change_4": null,
      "pct_change_4": null,
      "change_6": null,
      "pct_change_6": null,
      "change_12": null,
      "pct_change_12": null,
      "rolling_3": 115568686.0,
      "rolling_4": 115568686.0,
      "rolling_6": 115568686.0,
      "rolling_12": 115568686.0,
      "index_first_100": 100.0
    },
    {
      "indicator_id": "qcew_total_private_employment_annual",
      "date": "2015-01-01",
      "value": 118307717.0,
      "source": "bls_qcew_open_data",
      "series_id": "qcew:US000:private:10:annual_avg_emplvl",
      "frequency": "A",
      "seasonal_adjustment": "NSA",
      "units": "Jobs",
      "realtime_start": null,
      "realtime_end": null,
      "footnotes": "area_fips=US000; industry_code=10; own_code=5; agglvl_code=11",
      "geography": "US",
      "geo_id": "US",
      "geo_label": "US",
      "entity_key": "qcew_total_private_employment_annual|US",
      "change_1": 2739031.0,
      "pct_change_1": 2.370045982871183,
      "change_3": null,
      "pct_change_3": null,
      "change_4": null,
      "pct_change_4": null,
      "change_6": null,
      "pct_change_6": null,
      "change_12": null,
      "pct_change_12": null,
      "rolling_3": 116938201.5,
      "rolling_4": 116938201.5,
      "rolling_6": 116938201.5,
      "rolling_12": 116938201.5,
      "index_first_100": 102.37004598287118
    },
    {
      "indicator_id": "qcew_total_private_employment_annual",
      "date": "2016-01-01",
      "value": 120504622.0,
      "source": "bls_qcew_open_data",
      "series_id": "qcew:US000:private:10:annual_avg_emplvl",
      "frequency": "A",
      "seasonal_adjustment": "NSA",
      "units": "Jobs",
      "realtime_start": null,
      "realtime_end": null,
      "footnotes": "area_fips=US000; industry_code=10; own_code=5; agglvl_code=11",
      "geography": "US",
      "geo_id": "US",
      "geo_label": "US",
      "entity_key": "qcew_total_private_employment_annual|US",
      "change_1": 2196905.0,
      "pct_change_1": 1.8569414199751666,
      "change_3": null,
      "pct_change_3": null,
      "change_4": null,
      "pct_change_4": null,
      "change_6": null,
      "pct_change_6": null,
      "change_12": null,
      "pct_change_12": null,
      "rolling_3": 118127008.33333333,
      "rolling_4": 118127008.33333333,
      "rolling_6": 118127008.33333333,
      "rolling_12": 118127008.33333333,
      "index_first_100": 104.27099776837474
    },
    {
      "indicator_id": "qcew_total_private_employment_annual",
      "date": "2017-01-01",
      "value": 122386565.0,
      "source": "bls_qcew_open_data",
      "series_id": "qcew:US000:private:10:annual_avg_emplvl",
      "frequency": "A",
      "seasonal_adjustment": "NSA",
      "units": "Jobs",
      "realtime_start": null,
      "realtime_end": null,
      "footnotes": "area_fips=US000; industry_code=10; own_code=5; agglvl_code=11",
      "geography": "US",
      "geo_id": "US",
      "geo_label": "US",
      "entity_key": "qcew_total_private_employment_annual|US",
      "change_1": 1881943.0,
      "pct_change_1": 1.5617185206389772,
      "change_3": 6817879.0,
      "pct_change_3": 5.899417252178507,
      "change_4": null,
      "pct_change_4": null,
      "change_6": null,
      "pct_change_6": null,
      "change_12": null,
      "pct_change_12": null,
      "rolling_3": 120399634.66666667,
      "rolling_4": 119191897.5,
      "rolling_6": 119191897.5,
      "rolling_12": 119191897.5,
      "index_first_100": 105.89941725217851
    },
    {
      "indicator_id": "qcew_total_private_employment_annual",
      "date": "2018-01-01",
      "value": 124551838.0,
      "source": "bls_qcew_open_data",
      "series_id": "qcew:US000:private:10:annual_avg_emplvl",
      "frequency": "A",
      "seasonal_adjustment": "NSA",
      "units": "Jobs",
      "realtime_start": null,
      "realtime_end": null,
      "footnotes": "area_fips=US000; industry_code=10; own_code=5; agglvl_code=11",
      "geography": "US",
      "geo_id": "US",
      "geo_label": "US",
      "entity_key": "qcew_total_private_employment_annual|US",
      "change_1": 2165273.0,
      "pct_change_1": 1.7692080826028578,
      "change_3": 6244121.0,
      "pct_change_3": 5.2778645031245075,
      "change_4": 8983152.0,
      "pct_change_4": 7.77299830163336,
      "change_6": null,
      "pct_change_6": null,
      "change_12": null,
      "pct_change_12": null,
      "rolling_3": 122481008.33333333,
      "rolling_4": 121437685.5,
      "rolling_6": 120263885.6,
      "rolling_12": 120263885.6,
      "index_first_100": 107.77299830163336
    },
    {
      "indicator_id": "qcew_total_private_employment_annual",
      "date": "2019-01-01",
      "value": 126358743.0,
      "source": "bls_qcew_open_data",
      "series_id": "qcew:US000:private:10:annual_avg_emplvl",
      "frequency": "A",
      "seasonal_adjustment": "NSA",
      "units": "Jobs",
      "realtime_start": null,
      "realtime_end": null,
      "footnotes": "area_fips=US000; industry_code=10; own_code=5; agglvl_code=11",
      "geography": "US",
      "geo_id": "US",
      "geo_label": "US",
      "entity_key": "qcew_total_private_employment_annual|US",
      "change_1": 1806905.0,
      "pct_change_1": 1.4507252795418424,
      "change_3": 5854121.0,
      "pct_change_3": 4.858005363478912,
      "change_4": 8051026.0,
      "pct_change_4": 6.80515709723315,
      "change_6": null,
      "pct_change_6": null,
      "change_12": null,
      "pct_change_12": null,
      "rolling_3": 124432382.0,
      "rolling_4": 123450442.0,
      "rolling_6": 121279695.16666667,
      "rolling_12": 121279695.16666667,
      "index_first_100": 109.33648843251535
    },
    {
      "indicator_id": "qcew_total_private_employment_annual",
      "date": "2020-01-01",
      "value": 117940012.0,
      "source": "bls_qcew_open_data",
      "series_id": "qcew:US000:private:10:annual_avg_emplvl",
      "frequency": "A",
      "seasonal_adjustment": "NSA",
      "units": "Jobs",
      "realtime_start": null,
      "realtime_end": null,
      "footnotes": "area_fips=US000; industry_code=10; own_code=5; agglvl_code=11",
      "geography": "US",
      "geo_id": "US",
      "geo_label": "US",
      "entity_key": "qcew_total_private_employment_annual|US",
      "change_1": -8418731.0,
      "pct_change_1": -6.662563112075281,
      "change_3": -4446553.0,
      "pct_change_3": -3.6332035301423815,
      "change_4": -2564610.0,
      "pct_change_4": -2.1282254219261443,
      "change_6": 2371326.0,
      "pct_change_6": 2.0518758861721498,
      "change_12": null,
      "pct_change_12": null,
      "rolling_3": 122950197.66666667,
      "rolling_4": 122809289.5,
      "rolling_6": 121674916.16666667,
      "rolling_12": 120802597.57142857,
      "index_first_100": 102.05187588617216
    },
    {
      "indicator_id": "qcew_total_private_employment_annual",
      "date": "2021-01-01",
      "value": 122716652.0,
      "source": "bls_qcew_open_data",
      "series_id": "qcew:US000:private:10:annual_avg_emplvl",
      "frequency": "A",
      "seasonal_adjustment": "NSA",
      "units": "Jobs",
      "realtime_start": null,
      "realtime_end": null,
      "footnotes": "area_fips=US000; industry_code=10; own_code=5; agglvl_code=11",
      "geography": "US",
      "geo_id": "US",
      "geo_label": "US",
      "entity_key": "qcew_total_private_employment_annual|US",
      "change_1": 4776640.0,
      "pct_change_1": 4.050058940133061,
      "change_3": -1835186.0,
      "pct_change_3": -1.4734314880202715,
      "change_4": 330087.0,
      "pct_change_4": 0.2697085256049059,
      "change_6": 4408935.0,
      "pct_change_6": 3.7266672976201454,
      "change_12": null,
      "pct_change_12": null,
      "rolling_3": 122338469.0,
      "rolling_4": 122891811.25,
      "rolling_6": 122409738.66666667,
      "rolling_12": 121041854.375,
      "index_first_100": 106.18503700907355
    },
    {
      "indicator_id": "qcew_total_private_employment_annual",
      "date": "2022-01-01",
      "value": 128718060.0,
      "source": "bls_qcew_open_data",
      "series_id": "qcew:US000:private:10:annual_avg_emplvl",
      "frequency": "A",
      "seasonal_adjustment": "NSA",
      "units": "Jobs",
      "realtime_start": null,
      "realtime_end": null,
      "footnotes": "area_fips=US000; industry_code=10; own_code=5; agglvl_code=11",
      "geography": "US",
      "geo_id": "US",
      "geo_label": "US",
      "entity_key": "qcew_total_private_employment_annual|US",
      "change_1": 6001408.0,
      "pct_change_1": 4.8904593648790184,
      "change_3": 2359317.0,
      "pct_change_3": 1.8671577003579465,
      "change_4": 4166222.0,
      "pct_change_4": 3.344970308667783,
      "change_6": 8213438.0,
      "pct_change_6": 6.815869685064868,
      "change_12": null,
      "pct_change_12": null,
      "rolling_3": 123124908.0,
      "rolling_4": 123933366.75,
      "rolling_6": 123778645.0,
      "rolling_12": 121894766.1111111,
      "index_first_100": 111.37797309558404
    },
    {
      "indicator_id": "qcew_total_private_employment_annual",
      "date": "2023-01-01",
      "value": 131289681.0,
      "source": "bls_qcew_open_data",
      "series_id": "qcew:US000:private:10:annual_avg_emplvl",
      "frequency": "A",
      "seasonal_adjustment": "NSA",
      "units": "Jobs",
      "realtime_start": null,
      "realtime_end": null,
      "footnotes": "area_fips=US000; industry_code=10; own_code=5; agglvl_code=11",
      "geography": "US",
      "geo_id": "US",
      "geo_label": "US",
      "entity_key": "qcew_total_private_employment_annual|US",
      "change_1": 2571621.0,
      "pct_change_1": 1.9978711612030242,
      "change_3": 13349669.0,
      "pct_change_3": 11.319033103032083,
      "change_4": 4930938.0,
      "pct_change_4": 3.902332266790598,
      "change_6": 8903116.0,
      "pct_change_6": 7.274586062612354,
      "change_12": null,
      "pct_change_12": null,
      "rolling_3": 127574797.66666667,
      "rolling_4": 125166101.25,
      "rolling_6": 125262497.66666667,
      "rolling_12": 122834257.6,
      "index_first_100": 113.60316149999316
    },
    {
      "indicator_id": "qcew_total_private_employment_annual",
      "date": "2024-01-01",
      "value": 132569771.0,
      "source": "bls_qcew_open_data",
      "series_id": "qcew:US000:private:10:annual_avg_emplvl",
      "frequency": "A",
      "seasonal_adjustment": "NSA",
      "units": "Jobs",
      "realtime_start": null,
      "realtime_end": null,
      "footnotes": "area_fips=US000; industry_code=10; own_code=5; agglvl_code=11",
      "geography": "US",
      "geo_id": "US",
      "geo_label": "US",
      "entity_key": "qcew_total_private_employment_annual|US",
      "change_1": 1280090.0,
      "pct_change_1": 0.9750118899291005,
      "change_3": 9853119.0,
      "pct_change_3": 8.029162171080095,
      "change_4": 14629759.0,
      "pct_change_4": 12.404406911540766,
      "change_6": 8017933.0,
      "pct_change_6": 6.437426479406905,
      "change_12": null,
      "pct_change_12": null,
      "rolling_3": 130859170.66666667,
      "rolling_4": 128823541.0,
      "rolling_6": 126598819.83333333,
      "rolling_12": 123719304.27272727,
      "index_first_100": 114.71080583195348
    },
    {
      "indicator_id": "qcew_total_private_employment_annual",
      "date": "2025-01-01",
      "value": 133117983.0,
      "source": "bls_qcew_open_data",
      "series_id": "qcew:US000:private:10:annual_avg_emplvl",
      "frequency": "A",
      "seasonal_adjustment": "NSA",
      "units": "Jobs",
      "realtime_start": null,
      "realtime_end": null,
      "footnotes": "area_fips=US000; industry_code=10; own_code=5; agglvl_code=11",
      "geography": "US",
      "geo_id": "US",
      "geo_label": "US",
      "entity_key": "qcew_total_private_employment_annual|US",
      "change_1": 548212.0,
      "pct_change_1": 0.4135271531848783,
      "change_3": 4399923.0,
      "pct_change_3": 3.4182639172778195,
      "change_4": 10401331.0,
      "pct_change_4": 8.475892090015623,
      "change_6": 6759240.0,
      "pct_change_6": 5.34924599558575,
      "change_12": null,
      "pct_change_12": null,
      "rolling_3": 132325811.66666667,
      "rolling_4": 131423873.75,
      "rolling_6": 127725359.83333333,
      "rolling_12": 124502527.5,
      "index_first_100": 115.18516616170578
    }
  ]
}